{
  "gifs": [
    {
      "title": "GIF 1",
      "info": "120+ WPM, 95-100% ACC",
      "url": "https://giphy.com/embed/l0HlLWj5e25b5Ky76",
      "width": "480",
      "height": "385"
    },
    {
      "title": "GIF 2",
      "info": "120+ WPM, 95-100% ACC",
      "url": "https://giphy.com/embed/11BbGyhVmk4iLS",
      "width": "480",
      "height": "365"
    },
    {
      "title": "GIF 3",
      "info": "120+ WPM, 80-95% ACC",
      "url": "https://giphy.com/embed/PvvSfSDFoAL5e",
      "width": "480",
      "height": "360"
    },
    {
      "title": "GIF 4",
      "info": "120+ WPM, 80-95% ACC",
      "url": "https://giphy.com/embed/RRerwvHrb0nxm",
      "width": "480",
      "height": "270"
    },
    {
      "title": "GIF 5",
      "info": "60-120 WPM, 95-100% ACC",
      "url": "https://giphy.com/embed/BemKqR9RDK4V2",
      "width": "480",
      "height": "287"
    },
    {
      "title": "GIF 6",
      "info": "60-120 WPM, 95-100% ACC",
      "url": "https://giphy.com/embed/EoH4Wpu8suiNTLpI6j",
      "width": "480",
      "height": "480"
    },
    {
      "title": "GIF 7",
      "info": "60-120 WPM, 80-95% ACC",
      "url": "https://giphy.com/embed/UZQCbV4OW1mXdHJNPS",
      "width": "480",
      "height": "480"
    },
    {
      "title": "GIF 8",
      "info": "60-120 WPM, 80-95% ACC",
      "url": "https://giphy.com/embed/Wsju5zAb5kcOfxJV9i",
      "width": "480",
      "height": "480"
    },
    {
      "title": "GIF 9",
      "info": "40-60 WPM, 95-100% ACC",
      "url": "https://giphy.com/embed/IpeYSEZshTefe",
      "width": "480",
      "height": "344"
    },
    {
      "title": "GIF 10",
      "info": "40-60 WPM, 95-100% ACC",
      "url": "https://giphy.com/embed/1dHy0JSmsIfJgTgXEF",
      "width": "480",
      "height": "480"
    },
    {
      "title": "GIF 11",
      "info": "40-60 WPM, 80-95% ACC",
      "url": "https://giphy.com/embed/hwvxuIKLEayDS",
      "width": "480",
      "height": "354"
    },
    {
      "title": "GIF 12",
      "info": "40-60 WPM, 80-95% ACC",
      "url": "https://giphy.com/embed/3mKBXLpYeLzUY",
      "width": "480",
      "height": "384"
    },
    {
      "title": "GIF 13",
      "info": "0-40 WPM, 95-100% ACC",
      "url": "https://giphy.com/embed/l41JWwvf5k0GL1SuY",
      "width": "480",
      "height": "319"
    },
    {
      "title": "GIF 14",
      "info": "0-40 WPM, 95-100% ACC",
      "url": "https://giphy.com/embed/3o6ZsX2OZJ8G3Tec6Y",
      "width": "480",
      "height": "361"
    },
    {
      "title": "GIF 15",
      "info": "0-40 WPM, 80-95% ACC",
      "url": "https://giphy.com/embed/YAnpMSHcurJVS",
      "width": "480",
      "height": "360"
    },
    {
      "title": "GIF 16",
      "info": "0-40 WPM, 80-95% ACC",
      "url": "https://giphy.com/embed/iFU36VwXUd2O43gdcr",
      "width": "480",
      "height": "270"
    },
    {
      "title": "GIF 17",
      "info": "0-80% ACC",
      "url": "https://giphy.com/embed/11xBk5MoWjrYoE",
      "width": "480",
      "height": "480"
    },
    {
      "title": "GIF 18",
      "info": "0-80% ACC",
      "url": "https://giphy.com/embed/1qXc2onDaFpoHTgvHA",
      "width": "480",
      "height": "480"
    },
    {
      "title": "GIF 19",
      "info": "0-80% ACC",
      "url": "https://giphy.com/embed/UevalSWg5twQeqpc8Q",
      "width": "480",
      "height": "480"
    },
    {
      "title": "GIF 20",
      "info": "0-80% ACC",
      "url": "https://giphy.com/embed/9rv3RJwRmXWkISOUQc",
      "width": "480",
      "height": "270"
    }
  ]
}
